PyMovieI/__init__.py
PyMovieI/helper.py
PyMovieI-0.1.0.dist-info/LICENSE.txt
PyMovieI-0.1.0.dist-info/METADATA
PyMovieI-0.1.0.dist-info/WHEEL
PyMovieI-0.1.0.dist-info/top_level.txt
PyMovieI-0.1.0.dist-info/RECORD
