Metadata-Version: 2.1
Name: PyMovieI
Version: 0.1.0
Summary: PyMovieI is Python Library to fetch movie information and Movie Poster using Webscraping
Home-page: https://github.com/isameer11/PyMovieI
Author: Sameer Khan
Author-email: sameermadina786@gmail.com
License: MIT License (MIT)
Platform: UNKNOWN
Requires-Dist: bs4
Requires-Dist: google
Requires-Dist: requests
Requires-Dist: lxml
